elm_framework_helpers/__init__.py
elm_framework_helpers/ccxt/__init__.py
elm_framework_helpers/ccxt/models/orderbook.py
elm_framework_helpers/ccxt/orderbook/extract.py
elm_framework_helpers/config.py
elm_framework_helpers/http/__init__.py
elm_framework_helpers/http/threaded_server.py
elm_framework_helpers/json/__init__.py
elm_framework_helpers/logging.py
elm_framework_helpers/operators/__init__.py
elm_framework_helpers/operators/ignore_errors_.py
elm_framework_helpers/operators/item_at_index_.py
elm_framework_helpers/operators/manual_value_or.py
elm_framework_helpers/operators/retry_with_delay.py
elm_framework_helpers/output/__init__.py
elm_framework_helpers/schedulers/__init__.py
elm_framework_helpers/strategies/binance_tester.py
elm_framework_helpers/strategies/grid/orders.py
elm_framework_helpers/testing/__init__.py
elm_framework_helpers/testing/log_to_observable.py
elm_framework_helpers/testing/pytest/test_scheduler.py
elm_framework_helpers/testing/reactivex_assertion.py
elm_framework_helpers/unified/models/book.py
elm_framework_helpers/websocket_server/__init__.py
elm_framework_helpers/websocket_server/models.py
elm_framework_helpers/websocket_server/server.py
elm_framework_helpers/websocket_server/view.py
elm_framework_helpers/websockets/models/__init__.py
elm_framework_helpers/websockets/models/bundle.py
elm_framework_helpers/websockets/models/enhanced_websocket.py
elm_framework_helpers/websockets/models/message_types.py
elm_framework_helpers/websockets/models/status.py
elm_framework_helpers/websockets/operators/__init__.py
elm_framework_helpers/websockets/operators/connection_operators.py
elm_framework_helpers-0.3.1.dist-info/WHEEL
elm_framework_helpers-0.3.1.dist-info/METADATA
elm_framework_helpers-0.3.1.dist-info/RECORD
